{
  "subNodes": [
    {
      "idNum": 0,
      "orderNum": 0,
      "pcNode": true,
      "linkTo": 0,
      "ShowOnlyOnce": false,
      "NodeIsActive": true,
      "NodePortraitBitmap": "",
      "NodeNpcName": "",
      "NodeSound": "none",
      "conversationText": "root",
      "IsExpanded": true,
      "subNodes": [
        {
          "idNum": 1,
          "orderNum": 0,
          "pcNode": false,
          "linkTo": 0,
          "ShowOnlyOnce": true,
          "NodeIsActive": true,
          "NodePortraitBitmap": "",
          "NodeNpcName": "",
          "NodeSound": "none",
          "conversationText": "Hagmallow grew in the marshy ground. <FirstName> knew it by its violet flowers and sweet, carrion-like fragrance.\r\n\r\nThe plant made most people sleepy but energized witches.",
          "IsExpanded": true,
          "subNodes": [
            {
              "idNum": 2,
              "orderNum": 0,
              "pcNode": true,
              "linkTo": 0,
              "ShowOnlyOnce": false,
              "NodeIsActive": true,
              "NodePortraitBitmap": "",
              "NodeNpcName": "",
              "NodeSound": "none",
              "conversationText": "[Natural Philosophy: 50% chance of success -- Wisdom modifies] <He/She> carefully gathered the useful parts of the plant.",
              "IsExpanded": true,
              "subNodes": [
                {
                  "idNum": 14,
                  "orderNum": 0,
                  "pcNode": false,
                  "linkTo": 0,
                  "ShowOnlyOnce": false,
                  "NodeIsActive": true,
                  "NodePortraitBitmap": "",
                  "NodeNpcName": "",
                  "NodeSound": "none",
                  "conversationText": "[Success: 5 minutes pass.] <He/She> took three flowers.",
                  "IsExpanded": true,
                  "subNodes": [
                    {
                      "idNum": 17,
                      "orderNum": 0,
                      "pcNode": true,
                      "linkTo": 0,
                      "ShowOnlyOnce": false,
                      "NodeIsActive": true,
                      "NodePortraitBitmap": "",
                      "NodeNpcName": "",
                      "NodeSound": "none",
                      "conversationText": "[End.]",
                      "IsExpanded": true,
                      "subNodes": [],
                      "actions": [
                        {
                          "a_script": "gaGiveItem.cs",
                          "a_parameter_1": "hagmallow00",
                          "a_parameter_2": "3",
                          "a_parameter_3": null,
                          "a_parameter_4": null
                        },
                        {
                          "a_script": "gaShowMessageBox.cs",
                          "a_parameter_1": "Hagmallow (3) received!",
                          "a_parameter_2": null,
                          "a_parameter_3": null,
                          "a_parameter_4": null
                        },
                        {
                          "a_script": "gaSetGlobalInt.cs",
                          "a_parameter_1": "onmap",
                          "a_parameter_2": "1",
                          "a_parameter_3": null,
                          "a_parameter_4": null
                        }
                      ],
                      "conditions": [],
                      "isLink": false
                    }
                  ],
                  "actions": [],
                  "conditions": [
                    {
                      "c_script": "gcCheckAttribute.cs",
                      "c_btnAndOr": "and",
                      "c_and": true,
                      "c_not": false,
                      "c_parameter_1": "-1",
                      "c_parameter_2": "wis",
                      "c_parameter_3": ">",
                      "c_parameter_4": "13"
                    },
                    {
                      "c_script": "gcRand1of.cs",
                      "c_btnAndOr": "and",
                      "c_and": true,
                      "c_not": false,
                      "c_parameter_1": "5",
                      "c_parameter_2": null,
                      "c_parameter_3": null,
                      "c_parameter_4": null
                    }
                  ],
                  "isLink": false
                },
                {
                  "idNum": 15,
                  "orderNum": 1,
                  "pcNode": false,
                  "linkTo": 0,
                  "ShowOnlyOnce": false,
                  "NodeIsActive": true,
                  "NodePortraitBitmap": "",
                  "NodeNpcName": "",
                  "NodeSound": "none",
                  "conversationText": "[Success: 5 minutes pass.] <He/She> took two flowers.",
                  "IsExpanded": true,
                  "subNodes": [
                    {
                      "idNum": 18,
                      "orderNum": 0,
                      "pcNode": true,
                      "linkTo": 0,
                      "ShowOnlyOnce": false,
                      "NodeIsActive": true,
                      "NodePortraitBitmap": "",
                      "NodeNpcName": "",
                      "NodeSound": "none",
                      "conversationText": "[End.]",
                      "IsExpanded": true,
                      "subNodes": [],
                      "actions": [
                        {
                          "a_script": "gaGiveItem.cs",
                          "a_parameter_1": "hagmallow00",
                          "a_parameter_2": "2",
                          "a_parameter_3": null,
                          "a_parameter_4": null
                        },
                        {
                          "a_script": "gaShowMessageBox.cs",
                          "a_parameter_1": "Hagmallow (2) received!",
                          "a_parameter_2": null,
                          "a_parameter_3": null,
                          "a_parameter_4": null
                        },
                        {
                          "a_script": "gaSetGlobalInt.cs",
                          "a_parameter_1": "onmap",
                          "a_parameter_2": "1",
                          "a_parameter_3": null,
                          "a_parameter_4": null
                        }
                      ],
                      "conditions": [],
                      "isLink": false
                    }
                  ],
                  "actions": [],
                  "conditions": [
                    {
                      "c_script": "gcCheckAttribute.cs",
                      "c_btnAndOr": "and",
                      "c_and": true,
                      "c_not": false,
                      "c_parameter_1": "-1",
                      "c_parameter_2": "wis",
                      "c_parameter_3": ">",
                      "c_parameter_4": "10"
                    },
                    {
                      "c_script": "gcRand1of.cs",
                      "c_btnAndOr": "and",
                      "c_and": true,
                      "c_not": false,
                      "c_parameter_1": "2",
                      "c_parameter_2": null,
                      "c_parameter_3": null,
                      "c_parameter_4": null
                    }
                  ],
                  "isLink": false
                },
                {
                  "idNum": 16,
                  "orderNum": 2,
                  "pcNode": false,
                  "linkTo": 0,
                  "ShowOnlyOnce": false,
                  "NodeIsActive": true,
                  "NodePortraitBitmap": "",
                  "NodeNpcName": "",
                  "NodeSound": "none",
                  "conversationText": "[Failure: 5 minutes pass.] Unfortunately <he/she> found only one good flower.",
                  "IsExpanded": true,
                  "subNodes": [
                    {
                      "idNum": 19,
                      "orderNum": 0,
                      "pcNode": true,
                      "linkTo": 0,
                      "ShowOnlyOnce": false,
                      "NodeIsActive": true,
                      "NodePortraitBitmap": "",
                      "NodeNpcName": "",
                      "NodeSound": "none",
                      "conversationText": "[End.]",
                      "IsExpanded": true,
                      "subNodes": [],
                      "actions": [
                        {
                          "a_script": "gaGiveItem.cs",
                          "a_parameter_1": "hagmallow00",
                          "a_parameter_2": "1",
                          "a_parameter_3": null,
                          "a_parameter_4": null
                        },
                        {
                          "a_script": "gaShowMessageBox.cs",
                          "a_parameter_1": "Hagmallow received!",
                          "a_parameter_2": null,
                          "a_parameter_3": null,
                          "a_parameter_4": null
                        },
                        {
                          "a_script": "gaSetGlobalInt.cs",
                          "a_parameter_1": "onmap",
                          "a_parameter_2": "1",
                          "a_parameter_3": null,
                          "a_parameter_4": null
                        }
                      ],
                      "conditions": [],
                      "isLink": false
                    }
                  ],
                  "actions": [],
                  "conditions": [],
                  "isLink": false
                }
              ],
              "actions": [
                {
                  "a_script": "osSetProp.cs",
                  "a_parameter_1": "event1",
                  "a_parameter_2": null,
                  "a_parameter_3": "a",
                  "a_parameter_4": "false"
                },
                {
                  "a_script": "osSetProp.cs",
                  "a_parameter_1": "event1",
                  "a_parameter_2": null,
                  "a_parameter_3": "s",
                  "a_parameter_4": "false"
                },
                {
                  "a_script": "osSetWorldTime.cs",
                  "a_parameter_1": "+",
                  "a_parameter_2": "5",
                  "a_parameter_3": "false",
                  "a_parameter_4": null
                }
              ],
              "conditions": [
                {
                  "c_script": "gcCheckHasTrait.cs",
                  "c_btnAndOr": "and",
                  "c_and": true,
                  "c_not": false,
                  "c_parameter_1": "-1",
                  "c_parameter_2": "trait_naturalphil",
                  "c_parameter_3": null,
                  "c_parameter_4": null
                }
              ],
              "isLink": false
            },
            {
              "idNum": 20,
              "orderNum": 1,
              "pcNode": true,
              "linkTo": 0,
              "ShowOnlyOnce": false,
              "NodeIsActive": true,
              "NodePortraitBitmap": "",
              "NodeNpcName": "",
              "NodeSound": "none",
              "conversationText": "[Folk Magic: 80% chance of success -- Wisdom modifies] It could also be made into a garland to ward off hostile magics.",
              "IsExpanded": true,
              "subNodes": [
                {
                  "idNum": 21,
                  "orderNum": 0,
                  "pcNode": false,
                  "linkTo": 0,
                  "ShowOnlyOnce": false,
                  "NodeIsActive": true,
                  "NodePortraitBitmap": "",
                  "NodeNpcName": "",
                  "NodeSound": "none",
                  "conversationText": "[Success: 5 minutes pass.] <He/She> strung half a dozen or so of the blossoms together using a long piece of twine. ",
                  "IsExpanded": true,
                  "subNodes": [
                    {
                      "idNum": 27,
                      "orderNum": 0,
                      "pcNode": true,
                      "linkTo": 0,
                      "ShowOnlyOnce": false,
                      "NodeIsActive": true,
                      "NodePortraitBitmap": "",
                      "NodeNpcName": "",
                      "NodeSound": "none",
                      "conversationText": "[Continue.]",
                      "IsExpanded": true,
                      "subNodes": [
                        {
                          "idNum": 28,
                          "orderNum": 0,
                          "pcNode": false,
                          "linkTo": 0,
                          "ShowOnlyOnce": false,
                          "NodeIsActive": true,
                          "NodePortraitBitmap": "",
                          "NodeNpcName": "",
                          "NodeSound": "none",
                          "conversationText": "It was a delicate task, and the result was unlovely, but at the end of several minutes the young witch had an enchanted garland.",
                          "IsExpanded": true,
                          "subNodes": [
                            {
                              "idNum": 29,
                              "orderNum": 0,
                              "pcNode": true,
                              "linkTo": 0,
                              "ShowOnlyOnce": false,
                              "NodeIsActive": true,
                              "NodePortraitBitmap": "",
                              "NodeNpcName": "",
                              "NodeSound": "none",
                              "conversationText": "[End.]",
                              "IsExpanded": true,
                              "subNodes": [],
                              "actions": [
                                {
                                  "a_script": "gaGiveItem.cs",
                                  "a_parameter_1": "hagmallow_lei",
                                  "a_parameter_2": "1",
                                  "a_parameter_3": null,
                                  "a_parameter_4": null
                                },
                                {
                                  "a_script": "gaShowMessageBox.cs",
                                  "a_parameter_1": "Hagmallow Garland received!",
                                  "a_parameter_2": null,
                                  "a_parameter_3": null,
                                  "a_parameter_4": null
                                },
                                {
                                  "a_script": "gaSetGlobalInt.cs",
                                  "a_parameter_1": "onmap",
                                  "a_parameter_2": "1",
                                  "a_parameter_3": null,
                                  "a_parameter_4": null
                                },
                                {
                                  "a_script": "osSetWorldTime.cs",
                                  "a_parameter_1": "+",
                                  "a_parameter_2": "5",
                                  "a_parameter_3": "false",
                                  "a_parameter_4": null
                                }
                              ],
                              "conditions": [],
                              "isLink": false
                            }
                          ],
                          "actions": [],
                          "conditions": [],
                          "isLink": false
                        }
                      ],
                      "actions": [],
                      "conditions": [],
                      "isLink": false
                    }
                  ],
                  "actions": [],
                  "conditions": [
                    {
                      "c_script": "gcPassSkillCheck.cs",
                      "c_btnAndOr": "and",
                      "c_and": true,
                      "c_not": false,
                      "c_parameter_1": "-1",
                      "c_parameter_2": "trait_folkmagic",
                      "c_parameter_3": "5",
                      "c_parameter_4": null
                    },
                    {
                      "c_script": "gcCheckHasTrait.cs",
                      "c_btnAndOr": "or",
                      "c_and": false,
                      "c_not": false,
                      "c_parameter_1": "-1",
                      "c_parameter_2": "trait_folkmagic3",
                      "c_parameter_3": null,
                      "c_parameter_4": null
                    }
                  ],
                  "isLink": false
                },
                {
                  "idNum": 22,
                  "orderNum": 1,
                  "pcNode": false,
                  "linkTo": 0,
                  "ShowOnlyOnce": false,
                  "NodeIsActive": true,
                  "NodePortraitBitmap": "",
                  "NodeNpcName": "",
                  "NodeSound": "none",
                  "conversationText": "[Failure: Wisdom too low] <He/She> picked several of the flowers and tried to string them together with a bit of twine. But the flowers kept falling apart, and the twine ended up being too short. <He/She> abandoned the project in frustration.",
                  "IsExpanded": true,
                  "subNodes": [
                    {
                      "idNum": 30,
                      "orderNum": 0,
                      "pcNode": true,
                      "linkTo": 2,
                      "ShowOnlyOnce": false,
                      "NodeIsActive": true,
                      "NodePortraitBitmap": "",
                      "NodeNpcName": "",
                      "NodeSound": "none",
                      "conversationText": "[Natural Philosophy: Herbalism Test] <He/She> carefully gathered the useful parts of the plant. [This takes 5 minutes.]",
                      "IsExpanded": true,
                      "subNodes": [],
                      "actions": [],
                      "conditions": [],
                      "isLink": true
                    },
                    {
                      "idNum": 23,
                      "orderNum": 1,
                      "pcNode": true,
                      "linkTo": 3,
                      "ShowOnlyOnce": false,
                      "NodeIsActive": true,
                      "NodePortraitBitmap": "",
                      "NodeNpcName": "",
                      "NodeSound": "none",
                      "conversationText": "<He/She> collected some. [This takes 5 minutes.]",
                      "IsExpanded": true,
                      "subNodes": [],
                      "actions": [],
                      "conditions": [],
                      "isLink": true
                    },
                    {
                      "idNum": 25,
                      "orderNum": 2,
                      "pcNode": true,
                      "linkTo": 0,
                      "ShowOnlyOnce": false,
                      "NodeIsActive": true,
                      "NodePortraitBitmap": "",
                      "NodeNpcName": "",
                      "NodeSound": "none",
                      "conversationText": "<He/She> left the hagmallow alone. [This provides experience.]",
                      "IsExpanded": true,
                      "subNodes": [],
                      "actions": [
                        {
                          "a_script": "osSetProp.cs",
                          "a_parameter_1": "event1",
                          "a_parameter_2": null,
                          "a_parameter_3": "s",
                          "a_parameter_4": "false"
                        },
                        {
                          "a_script": "osSetProp.cs",
                          "a_parameter_1": "event1",
                          "a_parameter_2": null,
                          "a_parameter_3": "a",
                          "a_parameter_4": "false"
                        },
                        {
                          "a_script": "gaSetGlobalInt.cs",
                          "a_parameter_1": "experience",
                          "a_parameter_2": "1",
                          "a_parameter_3": null,
                          "a_parameter_4": null
                        },
                        {
                          "a_script": "gaSetGlobalInt.cs",
                          "a_parameter_1": "onmap",
                          "a_parameter_2": "1",
                          "a_parameter_3": null,
                          "a_parameter_4": null
                        }
                      ],
                      "conditions": [],
                      "isLink": false
                    }
                  ],
                  "actions": [],
                  "conditions": [],
                  "isLink": false
                }
              ],
              "actions": [
                {
                  "a_script": "gaSetGlobalInt.cs",
                  "a_parameter_1": "global_hagmallowlei",
                  "a_parameter_2": "1",
                  "a_parameter_3": null,
                  "a_parameter_4": null
                },
                {
                  "a_script": "osSetProp.cs",
                  "a_parameter_1": "event1",
                  "a_parameter_2": null,
                  "a_parameter_3": "s",
                  "a_parameter_4": "false"
                },
                {
                  "a_script": "osSetProp.cs",
                  "a_parameter_1": "event1",
                  "a_parameter_2": null,
                  "a_parameter_3": "a",
                  "a_parameter_4": "false"
                }
              ],
              "conditions": [
                {
                  "c_script": "gcCheckGlobalInt.cs",
                  "c_btnAndOr": "and",
                  "c_and": true,
                  "c_not": true,
                  "c_parameter_1": "global_hagmallowlei",
                  "c_parameter_2": "=",
                  "c_parameter_3": "1",
                  "c_parameter_4": null
                },
                {
                  "c_script": "gcCheckHasTrait.cs",
                  "c_btnAndOr": "and",
                  "c_and": true,
                  "c_not": false,
                  "c_parameter_1": "-1",
                  "c_parameter_2": "trait_folkmagic",
                  "c_parameter_3": null,
                  "c_parameter_4": null
                }
              ],
              "isLink": false
            },
            {
              "idNum": 3,
              "orderNum": 2,
              "pcNode": true,
              "linkTo": 0,
              "ShowOnlyOnce": false,
              "NodeIsActive": true,
              "NodePortraitBitmap": "",
              "NodeNpcName": "",
              "NodeSound": "none",
              "conversationText": "<He/She> collected some. [This takes 5 minutes.]",
              "IsExpanded": true,
              "subNodes": [],
              "actions": [
                {
                  "a_script": "osSetProp.cs",
                  "a_parameter_1": "event1",
                  "a_parameter_2": null,
                  "a_parameter_3": "s",
                  "a_parameter_4": "false"
                },
                {
                  "a_script": "osSetProp.cs",
                  "a_parameter_1": "event1",
                  "a_parameter_2": null,
                  "a_parameter_3": "a",
                  "a_parameter_4": "false"
                },
                {
                  "a_script": "gaGiveItem.cs",
                  "a_parameter_1": "hagmallow00",
                  "a_parameter_2": "1",
                  "a_parameter_3": null,
                  "a_parameter_4": null
                },
                {
                  "a_script": "osSetWorldTime.cs",
                  "a_parameter_1": "+",
                  "a_parameter_2": "5",
                  "a_parameter_3": "false",
                  "a_parameter_4": null
                },
                {
                  "a_script": "gaShowMessageBox.cs",
                  "a_parameter_1": "Hagmallow received!",
                  "a_parameter_2": null,
                  "a_parameter_3": null,
                  "a_parameter_4": null
                },
                {
                  "a_script": "gaSetGlobalInt.cs",
                  "a_parameter_1": "onmap",
                  "a_parameter_2": "1",
                  "a_parameter_3": null,
                  "a_parameter_4": null
                }
              ],
              "conditions": [],
              "isLink": false
            },
            {
              "idNum": 6,
              "orderNum": 3,
              "pcNode": true,
              "linkTo": 0,
              "ShowOnlyOnce": false,
              "NodeIsActive": true,
              "NodePortraitBitmap": "",
              "NodeNpcName": "",
              "NodeSound": "none",
              "conversationText": "<He/She> left it alone. [This provides experience.]",
              "IsExpanded": true,
              "subNodes": [],
              "actions": [
                {
                  "a_script": "osSetProp.cs",
                  "a_parameter_1": "event1",
                  "a_parameter_2": null,
                  "a_parameter_3": "s",
                  "a_parameter_4": "false"
                },
                {
                  "a_script": "osSetProp.cs",
                  "a_parameter_1": "event1",
                  "a_parameter_2": null,
                  "a_parameter_3": "a",
                  "a_parameter_4": "false"
                },
                {
                  "a_script": "gaSetGlobalInt.cs",
                  "a_parameter_1": "experience",
                  "a_parameter_2": "1",
                  "a_parameter_3": null,
                  "a_parameter_4": null
                },
                {
                  "a_script": "gaSetGlobalInt.cs",
                  "a_parameter_1": "onmap",
                  "a_parameter_2": "1",
                  "a_parameter_3": null,
                  "a_parameter_4": null
                }
              ],
              "conditions": [],
              "isLink": false
            }
          ],
          "actions": [],
          "conditions": [],
          "isLink": false
        },
        {
          "idNum": 7,
          "orderNum": 1,
          "pcNode": false,
          "linkTo": 0,
          "ShowOnlyOnce": false,
          "NodeIsActive": true,
          "NodePortraitBitmap": "",
          "NodeNpcName": "",
          "NodeSound": "none",
          "conversationText": "More hagmallow grew here.",
          "IsExpanded": true,
          "subNodes": [
            {
              "idNum": 9,
              "orderNum": 0,
              "pcNode": true,
              "linkTo": 2,
              "ShowOnlyOnce": false,
              "NodeIsActive": true,
              "NodePortraitBitmap": "",
              "NodeNpcName": "",
              "NodeSound": "none",
              "conversationText": "[Natural Philosophy: Herbalism Test] <He/She> carefully gathered the useful parts of the plant. [This takes 5 minutes.]",
              "IsExpanded": true,
              "subNodes": [],
              "actions": [],
              "conditions": [],
              "isLink": true
            },
            {
              "idNum": 26,
              "orderNum": 1,
              "pcNode": true,
              "linkTo": 20,
              "ShowOnlyOnce": false,
              "NodeIsActive": true,
              "NodePortraitBitmap": "",
              "NodeNpcName": "",
              "NodeSound": "none",
              "conversationText": "[Folk Magic: Practical Magic Test] It could also be made into a garland to ward off hostile magics.",
              "IsExpanded": true,
              "subNodes": [],
              "actions": [],
              "conditions": [],
              "isLink": true
            },
            {
              "idNum": 10,
              "orderNum": 2,
              "pcNode": true,
              "linkTo": 3,
              "ShowOnlyOnce": false,
              "NodeIsActive": true,
              "NodePortraitBitmap": "",
              "NodeNpcName": "",
              "NodeSound": "none",
              "conversationText": "<He/She> collected some. [This takes 5 minutes.]",
              "IsExpanded": true,
              "subNodes": [],
              "actions": [],
              "conditions": [],
              "isLink": true
            },
            {
              "idNum": 13,
              "orderNum": 3,
              "pcNode": true,
              "linkTo": 6,
              "ShowOnlyOnce": false,
              "NodeIsActive": true,
              "NodePortraitBitmap": "",
              "NodeNpcName": "",
              "NodeSound": "none",
              "conversationText": "<He/She> left it alone. [This provides experience.]",
              "IsExpanded": true,
              "subNodes": [],
              "actions": [],
              "conditions": [],
              "isLink": true
            }
          ],
          "actions": [],
          "conditions": [],
          "isLink": false
        }
      ],
      "actions": [],
      "conditions": [],
      "isLink": false
    }
  ],
  "ConvoFileName": "hagmallow_con",
  "Narration": false,
  "PartyChat": false,
  "SpeakToMainPcOnly": true,
  "NpcPortraitBitmap": "it_hagmallow.png",
  "DefaultNpcName": "",
  "NextIdNum": 34
}